graphing_tui/__init__.py
graphing_tui/tui.py
graphing_tui/tui.tcss
graphing_tui-0.1.0.dist-info/METADATA
graphing_tui-0.1.0.dist-info/WHEEL
graphing_tui-0.1.0.dist-info/entry_points.txt
graphing_tui-0.1.0.dist-info/licenses/LICENSE
graphing_tui-0.1.0.dist-info/RECORD
