Metadata-Version: 2.4
Name: graphing-tui
Version: 0.1.0
Summary: A terminal-based user interface application for graphing mathematical functions.
Author-email: David Fokkema <davidfokkema@icloud.com>
License-Expression: MIT
License-File: LICENSE
Requires-Python: >=3.11
Requires-Dist: asteval>=1.0.6
Requires-Dist: libcst>=1.6.0
Requires-Dist: textual-plot>=0.2.0
Requires-Dist: textual>=2.1.2
